[
    {
        "groupname": "Statistical Computing Laboratory",
        "description": "Lorem ipsum dolor sit amet, consetetur sadipscing elitr, sed diam nonumy eirmod tempor invidunt ut labore et dolore magna aliquyam erat, sed diam voluptua. At vero eos et accusam et justo duo dolores et ea rebum. Stet clita kasd gubergren, no sea takimata sanctus est. Lorem ipsum dolor sit amet. Lorem ipsum dolor sit amet, consetetur sadipscing elitr, sed diam nonumy eirmod tempor invidunt ut labore et dolore magna aliquyam erat, sed diam voluptua. At vero eos et accusam et justo duo dolores et ea rebum. Stet clita kasd gubergren, no sea takimata sanctus est. Lorem ipsum dolor sit amet.Lorem ipsum dolor sit amet, consetetur sadipscing elitr, sed diam nonumy eirmod tempor invidunt ut labore et dolore magna aliquyam erat, sed diam voluptua. At vero eos et accusa.",
        "members": [
            {
                "name": "Mr.",
                "surname": "Bean1",
                "title": "mascotte",
                "image_name" : "random.jpg"
            },
            {
                "name": "name",
                "surname": "surname",
                "title": "title",
                "image_name" : "solomon" 
            },
            {
                "name": "name",
                "surname": "surname",
                "title": "title",
                "image_name" : "prof_b.png"
            },
            {
                "name": "name",
                "surname": "surname",
                "title": "title",
                "image_name" : "prof_c.jpg"
            },
            {
                "name": "name",
                "surname": "surname",
                "title": "title",
                "image_name" : ""
            },
            {
                "name": "name",
                "surname": "surname",
                "title": "title",
                "image_name" : "prof_e.jpg"
            },
            {
                "name": "name",
                "surname": "surname",
                "title": "title",
                "image_name" : "bean.jpg"
            }
        ]
    },
    {
        "groupname": "Advanced Computing Laboratory",
        "description": "The research of the Advanced Computing Laboratory is centered around the topic of multicore and manycore algorithms for computing applications on emerging high-performance computing (HPC) architectures. Typically, we drive research towards extreme-scale simulations in computational algorithms, application software, programming, and software tools. We are currently involved in several HPC and computing research and simulation projects that develop methods and applications targeted at the next generation of petaflop/exaflop architectures. Interdisciplinary cooperation is a key to the work of this group, which functions as a link between various branches of computer science, computing technology, and application areas ranging from applied mathematics, to various branches of the engineering and natural sciences.",
        "members": [
            {
                "name": "Olaf",
                "surname": "Schenk",
                "title": "Head",
                "image_name" : "olaf.schenk"
            },
            {
                "name": "Drosos",
                "surname": "Kourounis",
                "title": "Senior Researcher",
                "image_name" : ""
            },
            {
                "name": "Juraj",
                "surname": "Kardos",
                "title": "Postdoctoral Fellow",
                "image_name" : ""
            },
            {
                "name": "Dimosthenis",
                "surname": "Pasadakis",
                "title": "Ph.D. Student",
                "image_name" : ""
            },
            {
                "name": "Aryan",
                "surname": " Eftekhari",
                "title": "Ph.D. Student",
                "image_name" : ""
            },
            {
                "name": "Tim",
                "surname": " Holt ",
                "title": "Ph.D. Student",
                "image_name" : ""
            },
            {
                "name": "Lisa",
                "surname": "Gaedke-Merzhaeuser",
                "title": "Ph.D. Student",
                "image_name" : ""
            },
            {
                "name": "Radim",
                "surname": "Janalík",
                "title": "Ph.D. Student",
                "image_name" : ""
            }
        ]
    },
    {
        "groupname": "Scientific Computing Laboratory",
        "description": "Lorem ipsum dolor sit amet, consetetur sadipscing elitr, sed diam nonumy eirmod tempor invidunt ut labore et dolore magna aliquyam erat, sed diam voluptua. At vero eos et accusam et justo duo dolores et ea rebum. Stet clita kasd gubergren, no sea takimata sanctus est. Lorem ipsum dolor sit amet. Lorem ipsum dolor sit amet, consetetur sadipscing elitr, sed diam nonumy eirmod tempor invidunt ut labore et dolore magna aliquyam erat, sed diam voluptua. At vero eos et accusam et justo duo dolores et ea rebum. Stet clita kasd gubergren, no sea takimata sanctus est. Lorem ipsum dolor sit amet.Lorem ipsum dolor sit amet, consetetur sadipscing elitr, sed diam nonumy eirmod tempor invidunt ut labore et dolore magna aliquyam erat, sed diam voluptua. At vero eos et accusa.",
        "members": [
            {
                "name": "name",
                "surname": "surname",
                "title": "title",
                "image_name" : ""
            },
            {
                "name": "name",
                "surname": "surname",
                "title": "title",
                "image_name" : ""
            },
            {
                "name": "name",
                "surname": "surname",
                "title": "title",
                "image_name" : ""
            }

        ]
    },
    {
        "groupname": "Scientific Computing Laboratory A",
        "description": "Lorem ipsum dolor sit amet, consetetur sadipscing elitr, sed diam nonumy eirmod tempor invidunt ut labore et dolore magna aliquyam erat, sed diam voluptua. At vero eos et accusam et justo duo dolores et ea rebum. Stet clita kasd gubergren, no sea takimata sanctus est. Lorem ipsum dolor sit amet. Lorem ipsum dolor sit amet, consetetur sadipscing elitr, sed diam nonumy eirmod tempor invidunt ut labore et dolore magna aliquyam erat, sed diam voluptua. At vero eos et accusam et justo duo dolores et ea rebum. Stet clita kasd gubergren, no sea takimata sanctus est. Lorem ipsum dolor sit amet.Lorem ipsum dolor sit amet, consetetur sadipscing elitr, sed diam nonumy eirmod tempor invidunt ut labore et dolore magna aliquyam erat, sed diam voluptua. At vero eos et accusa.",
        "members": [
            {
                "name": "name",
                "surname": "surname",
                "title": "title",
                "image_name" : ""
            },
            {
                "name": "name",
                "surname": "surname",
                "title": "title",
                "image_name" : ""
            },
            {
                "name": "name",
                "surname": "surname",
                "title": "title",
                "image_name" : ""
            }

        ]
    }

]
